everest_optimizers/__init__.py
everest_optimizers/_conminmfd.py
everest_optimizers/_convert_constraints.py
everest_optimizers/_optbcqnewton.py
everest_optimizers/_optqnewton.py
everest_optimizers/_optqnips.py
everest_optimizers/_problem.py
everest_optimizers/_utils.py
everest_optimizers/minimize.py
everest_optimizers/pyoptpp/__init__.py
everest_optimizers/pyoptpp/_pyoptpp.cpython-312-x86_64-linux-gnu.so
everest_optimizers/pyoptpp/_pyoptpp.pyi
everest_optimizers/pyoptpp/py.typed
everest_optimizers/pyoptsparse/LICENSE
everest_optimizers/pyoptsparse/__init__.py
everest_optimizers/pyoptsparse/pyOpt_MPI.py
everest_optimizers/pyoptsparse/pyOpt_constraint.py
everest_optimizers/pyoptsparse/pyOpt_error.py
everest_optimizers/pyoptsparse/pyOpt_gradient.py
everest_optimizers/pyoptsparse/pyOpt_history.py
everest_optimizers/pyoptsparse/pyOpt_objective.py
everest_optimizers/pyoptsparse/pyOpt_optimization.py
everest_optimizers/pyoptsparse/pyOpt_optimizer.py
everest_optimizers/pyoptsparse/pyOpt_solution.py
everest_optimizers/pyoptsparse/pyOpt_types.py
everest_optimizers/pyoptsparse/pyOpt_utils.py
everest_optimizers/pyoptsparse/pyOpt_variable.py
everest_optimizers/pyoptsparse/pyCONMIN/LICENSE
everest_optimizers/pyoptsparse/pyCONMIN/__init__.py
everest_optimizers/pyoptsparse/pyCONMIN/conmin.cpython-312-x86_64-linux-gnu.so
everest_optimizers/pyoptsparse/pyCONMIN/pyCONMIN.py
everest_optimizers.libs/libblas-fe34f726.so.3.8.0
everest_optimizers.libs/libgfortran-83c28eba.so.5.0.0
everest_optimizers.libs/liblapack-31d7d384.so.3.8.0
everest_optimizers.libs/libquadmath-2284e583.so.0.0.0
everest_optimizers-0.4.0.dist-info/METADATA
everest_optimizers-0.4.0.dist-info/WHEEL
everest_optimizers-0.4.0.dist-info/RECORD
everest_optimizers-0.4.0.dist-info/licenses/LICENSE
everest_optimizers-0.4.0.dist-info/sboms/auditwheel.cdx.json
